atlax/__init__.py
atlax/atlax.py
atlax/common.py
atlax-0.0.1.dist-info/LICENSE
atlax-0.0.1.dist-info/METADATA
atlax-0.0.1.dist-info/WHEEL
atlax-0.0.1.dist-info/entry_points.txt
atlax-0.0.1.dist-info/top_level.txt
atlax-0.0.1.dist-info/RECORD
